{
    "/js/app.js": "/js/app.js",
    "/css/app.css": "/css/app.css",
    "/css/app-vuetify.css": "/css/app-vuetify.css",
    "/js/app.d509c787148800b1037c.hot-update.js": "/js/app.d509c787148800b1037c.hot-update.js",
    "/js/app.50e03e1f4f5a67583508.hot-update.js": "/js/app.50e03e1f4f5a67583508.hot-update.js",
    "/js/app.87cd957a3d461cf80276.hot-update.js": "/js/app.87cd957a3d461cf80276.hot-update.js",
    "/js/app.f905eb123fdaae3aefcd.hot-update.js": "/js/app.f905eb123fdaae3aefcd.hot-update.js",
    "/js/app.d6d325f36f8c1193ea67.hot-update.js": "/js/app.d6d325f36f8c1193ea67.hot-update.js",
    "/js/app.55c04bc143649cb5cb26.hot-update.js": "/js/app.55c04bc143649cb5cb26.hot-update.js",
    "/js/app.db2abadaf66f98974e42.hot-update.js": "/js/app.db2abadaf66f98974e42.hot-update.js",
    "/js/app.8778fda4455f403e0c32.hot-update.js": "/js/app.8778fda4455f403e0c32.hot-update.js",
    "/js/app.38d6f25b1d5e5dcf3d98.hot-update.js": "/js/app.38d6f25b1d5e5dcf3d98.hot-update.js",
    "/js/app.4ead46484750df2b43ba.hot-update.js": "/js/app.4ead46484750df2b43ba.hot-update.js",
    "/js/app.122bdeca311e12f6807f.hot-update.js": "/js/app.122bdeca311e12f6807f.hot-update.js",
    "/js/app.a7c84237777af91cea11.hot-update.js": "/js/app.a7c84237777af91cea11.hot-update.js",
    "/js/app.f754d704b04ed12bfb22.hot-update.js": "/js/app.f754d704b04ed12bfb22.hot-update.js",
    "/js/app.ba3cc383b12daf2b2ad8.hot-update.js": "/js/app.ba3cc383b12daf2b2ad8.hot-update.js",
    "/js/app.b66b10cf58e12ecad575.hot-update.js": "/js/app.b66b10cf58e12ecad575.hot-update.js",
    "/js/app.c66aa454fc4fc438e02e.hot-update.js": "/js/app.c66aa454fc4fc438e02e.hot-update.js",
    "/js/app.618201022d3211e4b305.hot-update.js": "/js/app.618201022d3211e4b305.hot-update.js",
    "/js/app.84cb4be744d53310ac65.hot-update.js": "/js/app.84cb4be744d53310ac65.hot-update.js",
    "/js/app.8c0ec5d68febd6b085bd.hot-update.js": "/js/app.8c0ec5d68febd6b085bd.hot-update.js",
    "/js/app.d2fae425fb23cbc60e34.hot-update.js": "/js/app.d2fae425fb23cbc60e34.hot-update.js",
    "/js/app.58c56b04740ddabef0ed.hot-update.js": "/js/app.58c56b04740ddabef0ed.hot-update.js",
    "/js/app.ab30edee58c537fc4575.hot-update.js": "/js/app.ab30edee58c537fc4575.hot-update.js",
    "/js/app.ae1acfa329eaa24cd9b2.hot-update.js": "/js/app.ae1acfa329eaa24cd9b2.hot-update.js",
    "/js/app.6f0744ad80870eec1022.hot-update.js": "/js/app.6f0744ad80870eec1022.hot-update.js",
    "/js/app.4bd6230e825b4e5adfbe.hot-update.js": "/js/app.4bd6230e825b4e5adfbe.hot-update.js",
    "/js/app.1160cfb86abd60904f23.hot-update.js": "/js/app.1160cfb86abd60904f23.hot-update.js",
    "/js/app.1c1d09735a5bb2d356cc.hot-update.js": "/js/app.1c1d09735a5bb2d356cc.hot-update.js"
}
