[{"name":"lidc","value":"\"b=TB24:g=3511:u=1:i=1587366734:t=1587452989:s=AQHBaR46_XJnjfXzlubW5yRoQrm5glSk\"","domain":".linkedin.com","path":"/","expires":1587452986.491624,"size":84,"httpOnly":false,"secure":true,"session":false,"sameSite":"None"},{"name":"lang","value":"v=2&lang=en-us","domain":".linkedin.com","path":"/","expires":-1,"size":18,"httpOnly":false,"secure":true,"session":true,"sameSite":"None"},{"name":"sl","value":"v=1&3rxiL","domain":".www.linkedin.com","path":"/","expires":1595142731.112686,"size":11,"httpOnly":false,"secure":true,"session":false,"sameSite":"None"},{"name":"li_at","value":"AQEDATBUl7ADJAIRAAABcZZuKl4AAAFxunquXk0Ak3QyzQ9AEirq8yV7P-FaSx5Lq1mTiDovnq4K9eebwA4H_M64r85mTxs6DbOWcmx910LW20jexCGcVnQ7yROIfFg0SVzDmCmLqbvlBkkvOX30Pfao","domain":".www.linkedin.com","path":"/","expires":1618902731.112651,"size":157,"httpOnly":true,"secure":true,"session":false,"sameSite":"None"},{"name":"lissc","value":"1","domain":".linkedin.com","path":"/","expires":1618902729.458309,"size":6,"httpOnly":false,"secure":true,"session":false,"sameSite":"None"},{"name":"bscookie","value":"\"v=1&20200420071212c7d93294-af40-4378-8e32-d0fcffe059fdAQEObrrKLq5DLr-p0rkubujbXnlaef6o\"","domain":".www.linkedin.com","path":"/","expires":1650480581.458252,"size":96,"httpOnly":true,"secure":true,"session":false,"sameSite":"None"},{"name":"bcookie","value":"\"v=2&8a3b6b8c-1a66-4405-805d-7b10c6cc14ee\"","domain":".linkedin.com","path":"/","expires":1650480581.458012,"size":49,"httpOnly":false,"secure":true,"session":false,"sameSite":"None"},{"name":"JSESSIONID","value":"\"ajax:1574459127243314410\"","domain":".www.linkedin.com","path":"/","expires":1595142731.112758,"size":36,"httpOnly":false,"secure":true,"session":false,"sameSite":"None"},{"name":"liap","value":"true","domain":".linkedin.com","path":"/","expires":1595142731.112717,"size":8,"httpOnly":false,"secure":true,"session":false,"sameSite":"None"},{"name":"li_rm","value":"AQHQyO_OqY4PpAAAAXGWbiQkJkyQ9UbWCWLt41c5i64HJ6HOLyRuoSi__mdouwdjPYMoP5FFoxe6x7HVLYSJb3CobreX3bL8pXfni-n9yZdu4Mugx-0srBgy","domain":".www.linkedin.com","path":"/","expires":1618902731.112523,"size":125,"httpOnly":true,"secure":true,"session":false,"sameSite":"None"}]